stdatm/__init__.py
stdatm/atmosphere.py
stdatm/atmosphere_partials.py
stdatm/partials_state_parameters.py
stdatm/speed_parameters.py
stdatm/state_parameters.py
stdatm-0.4.3.dist-info/LICENSE
stdatm-0.4.3.dist-info/METADATA
stdatm-0.4.3.dist-info/WHEEL
stdatm-0.4.3.dist-info/RECORD
