Metadata-Version: 2.1
Name: stdatm
Version: 0.4.3
Summary: Numpy-oriented Standard Atmosphere model
License: GPL-3.0-only
Author: Christophe DAVID
Author-email: christophe.david@onera.fr
Requires-Python: >=3.8,<4.0
Classifier: Development Status :: 4 - Beta
Classifier: Environment :: Console
Classifier: Intended Audience :: Education
Classifier: Intended Audience :: Science/Research
Classifier: License :: OSI Approved :: GNU General Public License v3 (GPLv3)
Classifier: Natural Language :: English
Classifier: Operating System :: MacOS
Classifier: Operating System :: Microsoft :: Windows
Classifier: Operating System :: POSIX :: Linux
Classifier: Programming Language :: Python :: 3
Classifier: Programming Language :: Python :: 3.8
Classifier: Programming Language :: Python :: 3.9
Classifier: Programming Language :: Python :: 3.10
Classifier: Programming Language :: Python :: 3.11
Classifier: Programming Language :: Python :: 3.12
Classifier: Topic :: Scientific/Engineering :: Physics
Requires-Dist: numpy (>=1.22.0,<1.25) ; python_version >= "3.8" and python_version < "3.9"
Requires-Dist: numpy (>=1.23.2,<3) ; python_version >= "3.9" and python_version < "3.12"
Requires-Dist: numpy (>=1.26,<3) ; python_version >= "3.12" and python_version < "4.0"
Requires-Dist: scipy (>=1.10,<2.0) ; python_version >= "3.9" and python_version < "3.12"
Requires-Dist: scipy (>=1.11.2,<2.0.0) ; python_version >= "3.12" and python_version < "4.0"
Requires-Dist: scipy (>=1.9.3,<1.11) ; python_version >= "3.8" and python_version < "3.9"
